setup.py
qzonesecret/__init__.py
qzonesecret/secret.py
qzonesecret.egg-info/PKG-INFO
qzonesecret.egg-info/SOURCES.txt
qzonesecret.egg-info/dependency_links.txt
qzonesecret.egg-info/top_level.txt
qzonesecret.egg-info/zip-safe