Metadata-Version: 1.1
Name: qzonesecret
Version: 0.14
Summary: Find secrets in Qzone of any QQ.
Home-page: https://pypi.python.org/pypi/qzonesecret/
Author: Charles Yang
Author-email: mryang@minelandcn.com
License: MIT
Keywords: Qzone python QQ
Platform: UNKNOWN
Classifier: License :: OSI Approved :: MIT License
Classifier: Programming Language :: Python
Classifier: Intended Audience :: Developers
Classifier: Operating System :: OS Independent
